{
  "sejarah": "Yogyakarta, atau sering disebut Jogja, bukan sekadar kota wisata biasa. Ia adalah kota yang lahir dari perlawanan, diplomasi, dan filosofi mendalam yang masih hidup hingga hari ini.",
  "fasilitas": "Parkir luas, Mushola, Toilet umum, Homestay, Guide lokal, WiFi area pusat, Pusat informasi wisata, ATM center",
  "jam_operasional": "Senin-Minggu: 24 Jam (Layanan Informasi: 07.00 - 17.00 WIB)",
  "tiket": "Rp 15.000/orang (termasuk asuransi dasar)",
  "layanan_publik": {
    "rumah_sakit": [
      {
        "nama": "RSUP Dr. Sardjito",
        "alamat": "Jl. Kesehatan No. 1, Sekip, Yogyakarta",
        "telepon": "(0274) 587333",
        "cp": "IGD: (0274) 631190",
        "kategori": "Rumah Sakit Umum Pusat",
        "website": "https://sardjito.co.id",
        "foto": "https://images.unsplash.com/photo-1519494026892-80bbd2d6fd0d?w=800"
      },
      {
        "nama": "RS PKU Muhammadiyah Yogyakarta",
        "alamat": "Jl. KH. Ahmad Dahlan No. 20, Yogyakarta",
        "telepon": "(0274) 512653",
        "cp": "Info: (0274) 512653",
        "kategori": "Rumah Sakit Umum",
        "website": "https://pkuyogyakarta.com",
        "foto": "https://images.unsplash.com/photo-1587351021759-3e566b2af7cc?w=800"
      }
    ],
    "kantor_pelayanan": [
      {
        "nama": "Dinas Dukcapil Kota Yogyakarta",
        "alamat": "Jl. Suroto No. 2, Kotabaru, Yogyakarta",
        "telepon": "(0274) 563636",
        "cp": "Layanan: (0274) 563636",
        "jam_kerja": "Senin-Jumat: 08.00-15.00 WIB",
        "website": "https://disdukcapil.jogjakota.go.id",
        "foto": "https://images.unsplash.com/photo-1497366216548-37526070297c?w=800"
      }
    ],
    "pemerintah_daerah": [
      {
        "nama": "Dinas Pariwisata DIY",
        "alamat": "Jl. Cendana No. 11, Yogyakarta",
        "telepon": "(0274) 513333",
        "email": "pariwisata@jogjaprov.go.id",
        "website": "https://dispar.jogjaprov.go.id",
        "foto": "https://images.unsplash.com/photo-1555400038-63f5ba517a47?w=800"
      }
    ],
    "pendidikan": {
      "sd": [
        {
          "nama": "SD Negeri Kotabaru 1",
          "jenjang": "SD",
          "alamat": "Jl. Kotabaru No. 15, Yogyakarta",
          "telepon": "(0274) 512345",
          "cp": "Kepala Sekolah: Ibu Siti Aminah",
          "website": "https://www.instagram.com/explore/locations/323509333/sdn-ungaran-1---kotabaru-yogyakarta/",
          "foto": "https://www.sdnungaran1.sch.id/berita/read/SD-Negeri-Ungaran-1-Yogyakarta-mendapatkan-predikat-A-dalam-proses-akreditasi-tahun-2024"
        }
      ],
      "smp": [
        {
          "nama": "SMP Negeri 1 Yogyakarta",
          "jenjang": "SMP",
          "alamat": "Jl. AM Sangaji No. 40, Yogyakarta",
          "telepon": "(0274) 566666",
          "cp": "Kepala Sekolah: Bapak Budi Santoso",
          "website": "https://smpn1jogja.sch.id",
          "foto": "https://images.unsplash.com/photo-1523050854058-8df90110c9f1?w=800"
        }
      ],
      "sma": [
        {
          "nama": "SMA Negeri 1 Yogyakarta",
          "jenjang": "SMA",
          "alamat": "Jl. AM Sangaji No. 40, Yogyakarta",
          "telepon": "(0274) 566666",
          "cp": "Kepala Sekolah: Ibu Sri Wahyuni",
          "website": "https://sman1jogja.sch.id",
          "foto": "https://images.unsplash.com/photo-1562774053-701939374585?w=800"
        }
      ],
      "universitas": [
        {
          "nama": "Universitas Gadjah Mada (UGM)",
          "jenjang": "Universitas",
          "alamat": "Jl. Bulaksumur, Yogyakarta",
          "telepon": "(0274) 543434",
          "cp": "Humas: (0274) 543434",
          "website": "https://ugm.ac.id",
          "foto": "https://images.unsplash.com/photo-1562774053-701939374585?w=800"
        }
      ]
    }
  }
}